email_handler/__init__.py
email_handler/email_handler.py
email_handler-0.3.0.dist-info/METADATA
email_handler-0.3.0.dist-info/WHEEL
email_handler-0.3.0.dist-info/RECORD
