Metadata-Version: 2.1
Name: email_handler
Version: 0.3.0
Summary: A util to send emails
Author: Ashritha Shankar
Author-email: ashritha.shankar@solitontech.com
Requires-Python: >=3.12,<4.0
Classifier: Programming Language :: Python :: 3
Classifier: Programming Language :: Python :: 3.12
